<annotation>
	<folder>JPEGImages</folder>
	<filename>1_41.jpg</filename>
	<path>D:\download\baidu\fire_detection\fire_detection~\VOC2020\JPEGImages\1_41.jpg</path>
	<source>
		<database>Unknown</database>
	</source>
	<size>
		<width>2048</width>
		<height>1536</height>
		<depth>3</depth>
	</size>
	<segmented>0</segmented>
	<object>
		<name>fire</name>
		<pose>Unspecified</pose>
		<truncated>0</truncated>
		<difficult>0</difficult>
		<bndbox>
			<xmin>490</xmin>
			<ymin>156</ymin>
			<xmax>1616</xmax>
			<ymax>1223</ymax>
		</bndbox>
	</object>
	<object>
		<name>smoke</name>
		<pose>Unspecified</pose>
		<truncated>0</truncated>
		<difficult>0</difficult>
		<bndbox>
			<xmin>581</xmin>
			<ymin>28</ymin>
			<xmax>1283</xmax>
			<ymax>388</ymax>
		</bndbox>
	</object>
</annotation>
