<annotation>
	<folder>JPEGImages</folder>
	<filename>4aaececf-0e1d-4e3c-bfd2-67a69050854a.jpg</filename>
	<path>D:\data\VOC2020\JPEGImages\4aaececf-0e1d-4e3c-bfd2-67a69050854a.jpg</path>
	<source>
		<database>Unknown</database>
	</source>
	<size>
		<width>919</width>
		<height>611</height>
		<depth>3</depth>
	</size>
	<segmented>0</segmented>
	<object>
		<name>fire</name>
		<pose>Unspecified</pose>
		<truncated>0</truncated>
		<difficult>0</difficult>
		<bndbox>
			<xmin>252</xmin>
			<ymin>124</ymin>
			<xmax>768</xmax>
			<ymax>430</ymax>
		</bndbox>
	</object>
	<object>
		<name>smoke</name>
		<pose>Unspecified</pose>
		<truncated>0</truncated>
		<difficult>0</difficult>
		<bndbox>
			<xmin>165</xmin>
			<ymin>196</ymin>
			<xmax>364</xmax>
			<ymax>360</ymax>
		</bndbox>
	</object>
</annotation>
