<annotation>
	<folder>JPEGImages</folder>
	<filename>6077de90-937d-48cf-bc6f-7fdaefcc7898.jpg</filename>
	<path>D:\data\VOC2020\JPEGImages\6077de90-937d-48cf-bc6f-7fdaefcc7898.jpg</path>
	<source>
		<database>Unknown</database>
	</source>
	<size>
		<width>640</width>
		<height>478</height>
		<depth>3</depth>
	</size>
	<segmented>0</segmented>
	<object>
		<name>fire</name>
		<pose>Unspecified</pose>
		<truncated>0</truncated>
		<difficult>0</difficult>
		<bndbox>
			<xmin>101</xmin>
			<ymin>226</ymin>
			<xmax>514</xmax>
			<ymax>345</ymax>
		</bndbox>
	</object>
	<object>
		<name>smoke</name>
		<pose>Unspecified</pose>
		<truncated>0</truncated>
		<difficult>0</difficult>
		<bndbox>
			<xmin>91</xmin>
			<ymin>4</ymin>
			<xmax>552</xmax>
			<ymax>232</ymax>
		</bndbox>
	</object>
</annotation>
