<annotation>
	<folder>JPEGImages</folder>
	<filename>8199cca5-6ef9-4eb1-88ac-318665beea7b.jpg</filename>
	<path>D:\data\VOC2020\JPEGImages\8199cca5-6ef9-4eb1-88ac-318665beea7b.jpg</path>
	<source>
		<database>Unknown</database>
	</source>
	<size>
		<width>500</width>
		<height>334</height>
		<depth>3</depth>
	</size>
	<segmented>0</segmented>
	<object>
		<name>fire</name>
		<pose>Unspecified</pose>
		<truncated>0</truncated>
		<difficult>0</difficult>
		<bndbox>
			<xmin>169</xmin>
			<ymin>49</ymin>
			<xmax>481</xmax>
			<ymax>269</ymax>
		</bndbox>
	</object>
	<object>
		<name>smoke</name>
		<pose>Unspecified</pose>
		<truncated>0</truncated>
		<difficult>0</difficult>
		<bndbox>
			<xmin>205</xmin>
			<ymin>113</ymin>
			<xmax>399</xmax>
			<ymax>248</ymax>
		</bndbox>
	</object>
	<object>
		<name>smoke</name>
		<pose>Unspecified</pose>
		<truncated>1</truncated>
		<difficult>0</difficult>
		<bndbox>
			<xmin>41</xmin>
			<ymin>1</ymin>
			<xmax>176</xmax>
			<ymax>62</ymax>
		</bndbox>
	</object>
</annotation>
